MANIFEST.in
README.md
setup.py
corpus4classify/__init__.py
corpus4classify.egg-info/PKG-INFO
corpus4classify.egg-info/SOURCES.txt
corpus4classify.egg-info/dependency_links.txt
corpus4classify.egg-info/requires.txt
corpus4classify.egg-info/top_level.txt
corpus4classify/bbcnews/__init__.py
corpus4classify/bbcnews/extract_data.py
corpus4classify/bbcnews/transform_data.py
corpus4classify/bbcnews/data/business/001.txt
corpus4classify/bbcnews/data/business/002.txt
corpus4classify/bbcnews/data/business/003.txt
corpus4classify/bbcnews/data/business/004.txt
corpus4classify/bbcnews/data/business/005.txt
corpus4classify/bbcnews/data/business/006.txt
corpus4classify/bbcnews/data/business/007.txt
corpus4classify/bbcnews/data/business/008.txt
corpus4classify/bbcnews/data/business/009.txt
corpus4classify/bbcnews/data/business/010.txt
corpus4classify/bbcnews/data/business/011.txt
corpus4classify/bbcnews/data/business/012.txt
corpus4classify/bbcnews/data/business/013.txt
corpus4classify/bbcnews/data/business/014.txt
corpus4classify/bbcnews/data/business/015.txt
corpus4classify/bbcnews/data/business/016.txt
corpus4classify/bbcnews/data/business/017.txt
corpus4classify/bbcnews/data/business/018.txt
corpus4classify/bbcnews/data/business/019.txt
corpus4classify/bbcnews/data/business/020.txt
corpus4classify/bbcnews/data/business/021.txt
corpus4classify/bbcnews/data/business/022.txt
corpus4classify/bbcnews/data/business/023.txt
corpus4classify/bbcnews/data/business/024.txt
corpus4classify/bbcnews/data/business/025.txt
corpus4classify/bbcnews/data/business/026.txt
corpus4classify/bbcnews/data/business/027.txt
corpus4classify/bbcnews/data/business/028.txt
corpus4classify/bbcnews/data/business/029.txt
corpus4classify/bbcnews/data/business/030.txt
corpus4classify/bbcnews/data/business/031.txt
corpus4classify/bbcnews/data/business/032.txt
corpus4classify/bbcnews/data/business/033.txt
corpus4classify/bbcnews/data/business/034.txt
corpus4classify/bbcnews/data/business/035.txt
corpus4classify/bbcnews/data/business/036.txt
corpus4classify/bbcnews/data/business/037.txt
corpus4classify/bbcnews/data/business/038.txt
corpus4classify/bbcnews/data/business/039.txt
