Metadata-Version: 2.1
Name: corpus4classify
Version: 1.0.0
Summary: A number of corpora containing categorized documents for the use of text classification research.
Home-page: https://github.com/zjohn77/corpus4classify
Author: John Jung
Author-email: tojohnjung@gmail.com
License: MIT
Keywords: NLP-corpus
Platform: UNKNOWN
Classifier: Programming Language :: Python :: 3
Classifier: License :: OSI Approved :: MIT License
Classifier: Operating System :: POSIX :: Linux
